ip_acquirer_mcp/__init__.py
ip_acquirer_mcp-0.1.1.dist-info/METADATA
ip_acquirer_mcp-0.1.1.dist-info/WHEEL
ip_acquirer_mcp-0.1.1.dist-info/entry_points.txt
ip_acquirer_mcp-0.1.1.dist-info/licenses/LICENSE
ip_acquirer_mcp-0.1.1.dist-info/RECORD
