Metadata-Version: 2.4
Name: ip-acquirer-mcp
Version: 0.1.1
Summary: 一个通过 MCP 协议获取本机详细内网IP信息和公网IP的工具
Author-email: Zhengyi Chen <adamchenfr@gmail.com>
License: Copyright (c) 2025 Zhengyi Chen
License-File: LICENSE
Classifier: License :: OSI Approved :: MIT License
Classifier: Operating System :: OS Independent
Classifier: Programming Language :: Python :: 3
Requires-Python: >=3.8
Requires-Dist: mcp
Requires-Dist: psutil
Requires-Dist: requests
